hunting/__init__.py
hunting/admin.py
hunting/app_settings.py
hunting/apps.py
hunting/auth_hooks.py
hunting/checks.py
hunting/models.py
hunting/providers.py
hunting/tasks.py
hunting/urls.py
hunting/views.py
hunting/cogs/hunting.py
hunting/locale/da_DK/LC_MESSAGES/django.mo
hunting/locale/da_DK/LC_MESSAGES/django.po
hunting/locale/de/LC_MESSAGES/django.mo
hunting/locale/de/LC_MESSAGES/django.po
hunting/locale/en/LC_MESSAGES/django.po
hunting/locale/es/LC_MESSAGES/django.mo
hunting/locale/es/LC_MESSAGES/django.po
hunting/locale/fr_FR/LC_MESSAGES/django.mo
hunting/locale/fr_FR/LC_MESSAGES/django.po
hunting/locale/it_IT/LC_MESSAGES/django.mo
hunting/locale/it_IT/LC_MESSAGES/django.po
hunting/locale/ja/LC_MESSAGES/django.mo
hunting/locale/ja/LC_MESSAGES/django.po
hunting/locale/ko_KR/LC_MESSAGES/django.mo
hunting/locale/ko_KR/LC_MESSAGES/django.po
hunting/locale/ru/LC_MESSAGES/django.mo
hunting/locale/ru/LC_MESSAGES/django.po
hunting/locale/uk/LC_MESSAGES/django.mo
hunting/locale/uk/LC_MESSAGES/django.po
hunting/locale/zh_Hans/LC_MESSAGES/django.mo
hunting/locale/zh_Hans/LC_MESSAGES/django.po
hunting/migrations/0001_initial.py
hunting/migrations/0002_alter_locatechar_cache_expiry.py
hunting/migrations/0003_alter_agent_character_alter_agent_division.py
hunting/migrations/0004_alter_locatechar_locate_char_agent_alter_target_alts.py
hunting/migrations/0005_alter_agent_type.py
hunting/migrations/0006_alter_agent_type.py
hunting/migrations/__init__.py
hunting/templates/hunting/alt_details.html
hunting/templates/hunting/base-bs5.html
hunting/templates/hunting/index.html
hunting/templates/hunting/target_details.html
hunting/templates/hunting/target_details/locate_history.html
hunting/templatetags/hunting.py
hunting/tests/__init__.py
hunting/tests/create_eveuniverse_data.py
hunting/tests/eveuniverse.json
hunting/tests/load_eveuniverse.py
hunting/tests/test_app_settings.py
hunting/tests/test_models.py
aa_hunting-0.2.1a0.dist-info/licenses/LICENSE
aa_hunting-0.2.1a0.dist-info/WHEEL
aa_hunting-0.2.1a0.dist-info/METADATA
aa_hunting-0.2.1a0.dist-info/RECORD
